mentai/__init__.py
mentai/main.py
mentai/py.typed
mentai/menti/menti.py
mentai/menti/solver.py
mentai/menti/websocket.py
mentai/utils/__init__.py
mentai/utils/decorators.py
mentai/utils/logger.py
mentai/utils/settings.py
mentai/utils/styling.py
mentai/utils/types.py
mentai_cli-0.1.5.dist-info/licenses/LICENSE
mentai_cli-0.1.5.dist-info/METADATA
mentai_cli-0.1.5.dist-info/WHEEL
mentai_cli-0.1.5.dist-info/entry_points.txt
mentai_cli-0.1.5.dist-info/top_level.txt
mentai_cli-0.1.5.dist-info/RECORD
