Metadata-Version: 2.4
Name: mentai-cli
Version: 0.1.5
Summary: An automated CLI tool using AI to solve Menti quiz questions.
Author: Peter Schwips
License-Expression: MIT
Classifier: Development Status :: 4 - Beta
Classifier: Environment :: Console
Classifier: Intended Audience :: Education
Classifier: Intended Audience :: End Users/Desktop
Classifier: Natural Language :: English
Classifier: Operating System :: OS Independent
Classifier: Programming Language :: Python
Classifier: Programming Language :: Python :: 3.10
Classifier: Programming Language :: Python :: 3.11
Classifier: Programming Language :: Python :: 3.12
Classifier: Programming Language :: Python :: 3.13
Classifier: Topic :: Education :: Testing
Classifier: Topic :: Utilities
Classifier: Typing :: Typed
Requires-Python: >=3.10
License-File: LICENSE
Requires-Dist: fake-useragent>=2.2.0
Requires-Dist: openai>=1.102.0
Requires-Dist: platformdirs>=4.4.0
Requires-Dist: requests>=2.32.5
Requires-Dist: rich>=14.1.0
Requires-Dist: toml>=0.10.2
Requires-Dist: typer>=0.17.4
Requires-Dist: websocket-client>=1.8.0
Dynamic: license-file
